pulumi_hackweek/__init__.py
pulumi_hackweek/_utilities.py
pulumi_hackweek/hello_component.py
pulumi_hackweek/hello_world.py
pulumi_hackweek/provider.py
pulumi_hackweek/pulumi-plugin.json
pulumi_hackweek/py.typed
pulumi_hackweek-0.0.0.dist-info/METADATA
pulumi_hackweek-0.0.0.dist-info/WHEEL
pulumi_hackweek-0.0.0.dist-info/top_level.txt
pulumi_hackweek-0.0.0.dist-info/RECORD
